[
  {
    "key": "GWTZYPRF",
    "title": "The nature of microbubble emission under subcooled water boiling",
    "date": "02/2012",
    "doi": "10.1134/S0018151X12010208",
    "abstract_len": 422,
    "children": [
      {
        "key": "37S4VZP5",
        "itemType": "attachment",
        "title": "PDF",
        "contentType": "application/pdf",
        "filename": "Zeigarnik et al. - 2012 - The nature of microbubble emission under subcooled water boiling.pdf"
      }
    ],
    "fulltext_count": 1,
    "fulltext_chars": 18663
  },
  {
    "key": "VY3EMVUQ",
    "title": "Bubble-induced oscillating flow in microbubble emission boiling under highly subcooled conditions",
    "date": "2023-05-10",
    "doi": "10.1017/jfm.2023.285",
    "abstract_len": 1177,
    "children": [
      {
        "key": "I3VFJSVC",
        "itemType": "attachment",
        "title": "PDF",
        "contentType": "application/pdf",
        "filename": "Tang et al. - 2023 - Bubble-induced oscillating flow in microbubble emission boiling under highly subcooled conditions.pdf"
      }
    ],
    "fulltext_count": 1,
    "fulltext_chars": 46083
  },
  {
    "key": "NWAAUQCU",
    "title": "Micro-bubble emission boiling with the cavitation bubble blow pit",
    "date": "2016-09-15",
    "doi": "10.1038/srep33454",
    "abstract_len": 1098,
    "children": [
      {
        "key": "BAHAE7AQ",
        "itemType": "attachment",
        "title": "PDF",
        "contentType": "application/pdf",
        "filename": "Inada et al. - 2016 - Micro-bubble emission boiling with the cavitation bubble blow pit.pdf"
      }
    ],
    "fulltext_count": 1,
    "fulltext_chars": 31816
  },
  {
    "key": "5YJ3IL4Y",
    "title": "Deep learning the sound of boiling for advance prediction of boiling crisis",
    "date": "03/2021",
    "doi": "10.1016/j.xcrp.2021.100382",
    "abstract_len": 988,
    "children": [
      {
        "key": "LU7725E5",
        "itemType": "attachment",
        "title": "PDF",
        "contentType": "application/pdf",
        "filename": "Sinha et al. - 2021 - Deep learning the sound of boiling for advance prediction of boiling crisis.pdf"
      }
    ],
    "fulltext_count": 1,
    "fulltext_chars": 48354
  },
  {
    "key": "JAD7HI5P",
    "title": "Single-bubble water boiling on small heater under Earth\u2019s and low gravity",
    "date": "2018-11-02",
    "doi": "10.1038/s41526-018-0055-y",
    "abstract_len": 1311,
    "children": [
      {
        "key": "MS4H35K4",
        "itemType": "attachment",
        "title": "PDF",
        "contentType": "application/pdf",
        "filename": "Elele et al. - 2018 - Single-bubble water boiling on small heater under Earth\u2019s and low gravity.pdf"
      }
    ],
    "fulltext_count": 1,
    "fulltext_chars": 59270
  },
  {
    "key": "UGG5NPCI",
    "title": "Acoustic state detection of microbubble emission boiling using a deep neural network based on cepstrum analysis",
    "date": "09/2023",
    "doi": "10.1016/j.ijmultiphaseflow.2023.104512",
    "abstract_len": 1119,
    "children": [
      {
        "key": "CNNK9K3X",
        "itemType": "attachment",
        "title": "PDF",
        "contentType": "application/pdf",
        "filename": "Ono et al. - 2023 - Acoustic state detection of microbubble emission boiling using a deep neural network based on cepstr.pdf"
      }
    ],
    "fulltext_count": 1,
    "fulltext_chars": 29242
  },
  {
    "key": "SYSKAS7H",
    "title": "Simultaneous audio-visual-thermal characterization of transition boiling regime",
    "date": "10/2020",
    "doi": "10.1016/j.expthermflusci.2020.110162",
    "abstract_len": 1811,
    "children": [
      {
        "key": "T2ZMVHUH",
        "itemType": "attachment",
        "title": "PDF",
        "contentType": "application/pdf",
        "filename": "Nishant Ranjan Sinha et al. - 2020 - Simultaneous audio-visual-thermal characterization of transition boiling regime.pdf"
      }
    ],
    "fulltext_count": 1,
    "fulltext_chars": 56788
  },
  {
    "key": "ZK9RR7XG",
    "title": "A critical review on measures to suppress flow boiling instabilities in microchannels",
    "date": "06/2021",
    "doi": "10.1007/s00231-020-03009-2",
    "abstract_len": 1203,
    "children": [
      {
        "key": "AJ5GW55E",
        "itemType": "attachment",
        "title": "PDF",
        "contentType": "application/pdf",
        "filename": "Mao et al. - 2021 - A critical review on measures to suppress flow boiling instabilities in microchannels.pdf"
      }
    ],
    "fulltext_count": 1,
    "fulltext_chars": 81226
  },
  {
    "key": "VA7VCSNU",
    "title": "Enhanced Nucleate Pool Boiling by Coupling the Pinning Act and Cluster Bubble Nucleation of Micro-nano Composited Surfaces",
    "date": "08/2020",
    "doi": "10.1016/j.ijheatmasstransfer.2020.119979",
    "abstract_len": 1376,
    "children": [
      {
        "key": "VHHTR8WG",
        "itemType": "attachment",
        "title": "PDF",
        "contentType": "application/pdf",
        "filename": "Liu et al. - 2020 - Enhanced Nucleate Pool Boiling by Coupling the Pinning Act and Cluster Bubble Nucleation of Micro-na.pdf"
      }
    ],
    "fulltext_count": 1,
    "fulltext_chars": 57756
  },
  {
    "key": "BJUFH4C7",
    "title": "Diagnostics of coolant boiling onset based on the analysis of fluctuations of thermohydraulic parameters",
    "date": "2020-11-01",
    "doi": "10.1088/1742-6596/1689/1/012042",
    "abstract_len": 363,
    "children": [
      {
        "key": "N6YGEE25",
        "itemType": "attachment",
        "title": "PDF",
        "contentType": "application/pdf",
        "filename": "Litvintsova et al. - 2020 - Diagnostics of coolant boiling onset based on the analysis of fluctuations of thermohydraulic parame.pdf"
      }
    ],
    "fulltext_count": 1,
    "fulltext_chars": 23579
  },
  {
    "key": "J4SCVDJT",
    "title": "Acoustic emission monitoring of water boiling on fuel cladding surface at 1 bar and 130 bar",
    "date": "10/2017",
    "doi": "10.1016/j.measurement.2017.05.042",
    "abstract_len": 652,
    "children": [
      {
        "key": "QGCTSVYA",
        "itemType": "attachment",
        "title": "PDF",
        "contentType": "application/pdf",
        "filename": "Baek et al. - 2017 - Acoustic emission monitoring of water boiling on fuel cladding surface at 1 bar and 130 bar.pdf"
      }
    ],
    "fulltext_count": 1,
    "fulltext_chars": 36377
  },
  {
    "key": "RN8RNBPF",
    "title": "Spatial\u2013temporal thermal\u2010fluid behaviors of microbubble emission boiling (MEB)",
    "date": "08/2021",
    "doi": "10.1002/aic.17193",
    "abstract_len": 826,
    "children": [
      {
        "key": "2KCBGEB2",
        "itemType": "attachment",
        "title": "PDF",
        "contentType": "application/pdf",
        "filename": "Horiuchi et al. - 2021 - Spatial\u2013temporal thermal\u2010fluid behaviors of microbubble emission boiling (MEB).pdf"
      }
    ],
    "fulltext_count": 1,
    "fulltext_chars": 59655
  },
  {
    "key": "S24F4N22",
    "title": "Experimental investigation of transition process from nucleate boiling to microbubble emission boiling under transient heating modes",
    "date": "05/2019",
    "doi": "10.1002/aic.16555",
    "abstract_len": 953,
    "children": [
      {
        "key": "R35GEHHF",
        "itemType": "attachment",
        "title": "PDF",
        "contentType": "application/pdf",
        "filename": "Tang et al. - 2019 - Experimental investigation of transition process from nucleate boiling to microbubble emission boili.pdf"
      }
    ],
    "fulltext_count": 1,
    "fulltext_chars": 54732
  },
  {
    "key": "RQCEIE46",
    "title": "Acoustic State Sensing of Subcooled Boiling Heat Transfer on a CuCrZr Surface Using a Deep Neural Network for Divertor Application",
    "date": "2026-02-17",
    "doi": "10.1080/15361055.2024.2435193",
    "abstract_len": 1617,
    "children": [
      {
        "key": "HBCJPTQU",
        "itemType": "attachment",
        "title": "PDF",
        "contentType": "application/pdf",
        "filename": "Ueki et al. - 2026 - Acoustic State Sensing of Subcooled Boiling Heat Transfer on a CuCrZr Surface Using a Deep Neural Ne.pdf"
      }
    ],
    "fulltext_count": 1,
    "fulltext_chars": 21847
  },
  {
    "key": "MG7Y57I9",
    "title": "A visualized study of micro-bubble emission boiling",
    "date": "12/2014",
    "doi": "10.1016/j.icheatmasstransfer.2014.10.003",
    "abstract_len": 0,
    "children": [
      {
        "key": "KSI8AWLQ",
        "itemType": "attachment",
        "title": "PDF",
        "contentType": "application/pdf",
        "filename": "Zhu et al. - 2014 - A visualized study of micro-bubble emission boiling.pdf"
      }
    ],
    "fulltext_count": 1,
    "fulltext_chars": 22680
  },
  {
    "key": "RDTMXFSN",
    "title": "Effects of surface properties on wall superheat at the onset of microbubble emission boiling",
    "date": "10/2022",
    "doi": "10.1016/j.ijmultiphaseflow.2022.104196",
    "abstract_len": 1436,
    "children": [
      {
        "key": "ME4LJSBY",
        "itemType": "attachment",
        "title": "PDF",
        "contentType": "application/pdf",
        "filename": "Unno et al. - 2022 - Effects of surface properties on wall superheat at the onset of microbubble emission boiling.pdf"
      }
    ],
    "fulltext_count": 1,
    "fulltext_chars": 41665
  },
  {
    "key": "WELM2YER",
    "title": "High-frequency oscillation of coalesced vapor bubbles and resultant ambient liquid motion in microbubble emission boiling in subcooled pool",
    "date": "06/2025",
    "doi": "10.1016/j.ijheatmasstransfer.2025.126832",
    "abstract_len": 809,
    "children": [
      {
        "key": "Q8SYW6LQ",
        "itemType": "attachment",
        "title": "PDF",
        "contentType": "application/pdf",
        "filename": "Otake et al. - 2025 - High-frequency oscillation of coalesced vapor bubbles and resultant ambient liquid motion in microbu.pdf"
      }
    ],
    "fulltext_count": 1,
    "fulltext_chars": 61379
  },
  {
    "key": "23RAW57T",
    "title": "Onset of microbubble emission boiling at reduced pressure using a confined vessel for subcooled pool boiling",
    "date": "04/2025",
    "doi": "10.1016/j.ijheatmasstransfer.2024.126600",
    "abstract_len": 0,
    "children": [
      {
        "key": "J755X5K2",
        "itemType": "attachment",
        "title": "PDF",
        "contentType": "application/pdf",
        "filename": "Unno et al. - 2025 - Onset of microbubble emission boiling at reduced pressure using a confined vessel for subcooled pool.pdf"
      }
    ],
    "fulltext_count": 1,
    "fulltext_chars": 40163
  },
  {
    "key": "TRMXZ8KP",
    "title": "Flow microbubble emission boiling (MEB) in open microchannels for durable and efficient heat dissipation",
    "date": "03/2025",
    "doi": "10.1016/j.ijheatmasstransfer.2024.126506",
    "abstract_len": 2177,
    "children": [
      {
        "key": "LQ4NWRQH",
        "itemType": "attachment",
        "title": "PDF",
        "contentType": "application/pdf",
        "filename": "Zhao et al. - 2025 - Flow microbubble emission boiling (MEB) in open microchannels for durable and efficient heat dissipa.pdf"
      }
    ],
    "fulltext_count": 1,
    "fulltext_chars": 68474
  },
  {
    "key": "HJ49P5RB",
    "title": "On homogeneity of vapor bubbles\u2019 oscillation and corresponding heat transfer characteristics and boiling sound in microbubble emission boiling (MEB)",
    "date": "06/2022",
    "doi": "10.1016/j.ijheatmasstransfer.2022.122564",
    "abstract_len": 961,
    "children": [
      {
        "key": "26IHZUMP",
        "itemType": "attachment",
        "title": "PDF",
        "contentType": "application/pdf",
        "filename": "Kobayashi et al. - 2022 - On homogeneity of vapor bubbles\u2019 oscillation and corresponding heat transfer characteristics and boi.pdf"
      }
    ],
    "fulltext_count": 1,
    "fulltext_chars": 55458
  },
  {
    "key": "M7UNIG9L",
    "title": "Transition process leading to microbubble emission boiling on horizontal circular heated surface in subcooled pool",
    "date": "10/2016",
    "doi": "10.1016/j.ijheatmasstransfer.2016.05.050",
    "abstract_len": 1284,
    "children": [
      {
        "key": "8GNC39T8",
        "itemType": "attachment",
        "title": "PDF",
        "contentType": "application/pdf",
        "filename": "Ando et al. - 2016 - Transition process leading to microbubble emission boiling on horizontal circular heated surface in.pdf"
      }
    ],
    "fulltext_count": 1,
    "fulltext_chars": 51456
  },
  {
    "key": "RZQY5ISN",
    "title": "Experimental study of sound emission in subcooled pool boiling on a small heating surface",
    "date": "10/2018",
    "doi": "10.1016/j.ces.2018.05.002",
    "abstract_len": 1180,
    "children": [
      {
        "key": "8QIGALJC",
        "itemType": "attachment",
        "title": "PDF",
        "contentType": "application/pdf",
        "filename": "Tang et al. - 2018 - Experimental study of sound emission in subcooled pool boiling on a small heating surface.pdf"
      }
    ],
    "fulltext_count": 1,
    "fulltext_chars": 48931
  },
  {
    "key": "XF6L2UMH",
    "title": "Boiling of water at low pressure: the role of subcooling and thermophysical properties on the bubble dynamics and heat transfer",
    "date": null,
    "doi": null,
    "abstract_len": 0,
    "children": [
      {
        "key": "CHNP53UB",
        "itemType": "attachment",
        "title": "PDF",
        "contentType": "application/pdf",
        "filename": "Wojtasik - Boiling of water at low pressure the role of subcooling and thermophysical properties on the bubble.pdf"
      }
    ],
    "fulltext_count": 1,
    "fulltext_chars": 200000
  }
]